pysatSpaceWeather/__init__.py
pysatSpaceWeather/instruments/__init__.py
pysatSpaceWeather/instruments/ace_epam.py
pysatSpaceWeather/instruments/ace_mag.py
pysatSpaceWeather/instruments/ace_sis.py
pysatSpaceWeather/instruments/ace_swepam.py
pysatSpaceWeather/instruments/norp_rf.py
pysatSpaceWeather/instruments/sw_ae.py
pysatSpaceWeather/instruments/sw_al.py
pysatSpaceWeather/instruments/sw_ap.py
pysatSpaceWeather/instruments/sw_apo.py
pysatSpaceWeather/instruments/sw_au.py
pysatSpaceWeather/instruments/sw_cp.py
pysatSpaceWeather/instruments/sw_dst.py
pysatSpaceWeather/instruments/sw_f107.py
pysatSpaceWeather/instruments/sw_flare.py
pysatSpaceWeather/instruments/sw_hpo.py
pysatSpaceWeather/instruments/sw_kp.py
pysatSpaceWeather/instruments/sw_mgii.py
pysatSpaceWeather/instruments/sw_polarcap.py
pysatSpaceWeather/instruments/sw_sbfield.py
pysatSpaceWeather/instruments/sw_ssn.py
pysatSpaceWeather/instruments/sw_stormprob.py
pysatSpaceWeather/instruments/methods/__init__.py
pysatSpaceWeather/instruments/methods/ace.py
pysatSpaceWeather/instruments/methods/auroral_electrojet.py
pysatSpaceWeather/instruments/methods/dst.py
pysatSpaceWeather/instruments/methods/f107.py
pysatSpaceWeather/instruments/methods/general.py
pysatSpaceWeather/instruments/methods/gfz.py
pysatSpaceWeather/instruments/methods/kp_ap.py
pysatSpaceWeather/instruments/methods/lasp.py
pysatSpaceWeather/instruments/methods/lisird.py
pysatSpaceWeather/instruments/methods/norp.py
pysatSpaceWeather/instruments/methods/swpc.py
pysatSpaceWeather-0.2.1.dist-info/LICENSE
pysatSpaceWeather-0.2.1.dist-info/METADATA
pysatSpaceWeather-0.2.1.dist-info/WHEEL
pysatSpaceWeather-0.2.1.dist-info/top_level.txt
pysatSpaceWeather-0.2.1.dist-info/RECORD
