Metadata-Version: 2.1
Name: pysatSpaceWeather
Version: 0.2.1
Summary: pysat support for Space Weather Indices
Author-email: Angeline Burrell <pysat.developers@gmail.com>
License: BSD 3-Clause License
Project-URL: Documentation, https://pysatspaceweather.readthedocs.io/en/latest/
Project-URL: Source, https://github.com/pysat/pysatSpaceWeather
Keywords: pysat,ionosphere,heliophysics,magnetosphere,space-weather,forecasting,indexes
Classifier: Development Status :: 4 - Beta
Classifier: Topic :: Scientific/Engineering :: Astronomy
Classifier: Topic :: Scientific/Engineering :: Physics
Classifier: Topic :: Scientific/Engineering :: Atmospheric Science
Classifier: Intended Audience :: Science/Research
Classifier: License :: OSI Approved :: BSD License
Classifier: Natural Language :: English
Classifier: Programming Language :: Python :: 3
Classifier: Programming Language :: Python :: 3.9
Classifier: Programming Language :: Python :: 3.10
Classifier: Programming Language :: Python :: 3.11
Classifier: Programming Language :: Python :: 3.12
Classifier: Operating System :: POSIX :: Linux
Classifier: Operating System :: MacOS :: MacOS X
Classifier: Operating System :: Microsoft :: Windows
Requires-Python: >=3.9
License-File: LICENSE
Requires-Dist: netCDF4
Requires-Dist: numpy
Requires-Dist: packaging
Requires-Dist: pandas
Requires-Dist: pysat >=3.2.0
Requires-Dist: requests
Requires-Dist: xarray
Provides-Extra: doc
Requires-Dist: extras-require ; extra == 'doc'
Requires-Dist: ipython ; extra == 'doc'
Requires-Dist: m2r2 ; extra == 'doc'
Requires-Dist: numpydoc ; extra == 'doc'
Requires-Dist: pyproject-parser ; extra == 'doc'
Requires-Dist: sphinx ; extra == 'doc'
Requires-Dist: sphinx-rtd-theme <2.0.0,>=1.2.2 ; extra == 'doc'
Provides-Extra: test
Requires-Dist: flake8 ; extra == 'test'
Requires-Dist: flake8-docstrings ; extra == 'test'
Requires-Dist: hacking >=1.0 ; extra == 'test'
Requires-Dist: pytest ; extra == 'test'
Requires-Dist: pytest-cov ; extra == 'test'
Requires-Dist: pytest-ordering ; extra == 'test'
